microsoft_agents_m365copilot_beta/__init__.py
microsoft_agents_m365copilot_beta/_version.py
microsoft_agents_m365copilot_beta/agents_m365_copilot_beta_request_adapter.py
microsoft_agents_m365copilot_beta/agents_m365_copilot_beta_service_client.py
microsoft_agents_m365copilot_beta/generated/base_agents_m365_copilot_beta_service_client.py
microsoft_agents_m365copilot_beta/generated/copilot/admin/admin_request_builder.py
microsoft_agents_m365copilot_beta/generated/copilot/admin/catalog/catalog_request_builder.py
microsoft_agents_m365copilot_beta/generated/copilot/admin/catalog/packages/count/count_request_builder.py
microsoft_agents_m365copilot_beta/generated/copilot/admin/catalog/packages/item/copilot_package_detail_item_request_builder.py
microsoft_agents_m365copilot_beta/generated/copilot/admin/catalog/packages/packages_request_builder.py
microsoft_agents_m365copilot_beta/generated/copilot/admin/settings/limited_mode/limited_mode_request_builder.py
microsoft_agents_m365copilot_beta/generated/copilot/admin/settings/settings_request_builder.py
microsoft_agents_m365copilot_beta/generated/copilot/agents/agents_request_builder.py
microsoft_agents_m365copilot_beta/generated/copilot/agents/count/count_request_builder.py
microsoft_agents_m365copilot_beta/generated/copilot/agents/item/agent_item_request_builder.py
microsoft_agents_m365copilot_beta/generated/copilot/communications/communications_request_builder.py
microsoft_agents_m365copilot_beta/generated/copilot/communications/realtime_activity_feed/meetings/count/count_request_builder.py
microsoft_agents_m365copilot_beta/generated/copilot/communications/realtime_activity_feed/meetings/item/realtime_activity_meeting_item_request_builder.py
microsoft_agents_m365copilot_beta/generated/copilot/communications/realtime_activity_feed/meetings/item/transcripts/count/count_request_builder.py
microsoft_agents_m365copilot_beta-1.0.0rc14.dist-info/METADATA
microsoft_agents_m365copilot_beta-1.0.0rc14.dist-info/WHEEL
microsoft_agents_m365copilot_beta-1.0.0rc14.dist-info/RECORD
